{
  "name": "Force calculator",
  "model_path": "bouncing_ball",
  "server": "simulink2024a",
  "client": "openrti1516",
  "step_size": 0.005,
  "stop_time": 5.0,
  "formalism": "continuous",
  "outputs": [
    {
      "id": 0,
      "name": "h",
      "description": "Height of the ball",
      "type": "float64",
      "unit": "m",
      "default": 0.0,
      "namespace": "InteractionRoot"
    },
    {
      "id": 1,
      "name": "v",
      "description": "Velocity of the ball",
      "type": "float64",
      "unit": "m/s",
      "default": 0.0,
      "namespace": "InteractionRoot"
    }
  ],
  "parameters": [
    {
      "id": 0,
      "name": "g",
      "description": "Gravity",
      "type": "float64",
      "unit": "m/s^2",
      "default": 9.81,
      "namespace": "InteractionRoot.Parameters"
    },
    {
      "id": 1,
      "name": "e",
      "description": "Coefficient of restitution",
      "type": "float64",
      "default": 0.7,
      "namespace": "InteractionRoot.Parameters"
    },
    {
      "id": 2,
      "name": "h0",
      "description": "Initial height of the ball",
      "type": "float64",
      "unit": "m",
      "default": 5,
      "namespace": "InteractionRoot.Parameters"
    },
    {
      "id": 3,
      "name": "v0",
      "description": "Initial velocity of the ball",
      "type": "float64",
      "unit": "m/s",
      "default": 0.0,
      "namespace": "InteractionRoot.Parameters"
    }
  ]
}